README.md
setup.py
countmemaybe/__init__.py
countmemaybe/base_dve.py
countmemaybe/bloomfilter.py
countmemaybe/hyperloglog.py
countmemaybe/kminvalues.py
countmemaybe/quantile.py
countmemaybe/test_dve.py
countmemaybe.egg-info/PKG-INFO
countmemaybe.egg-info/SOURCES.txt
countmemaybe.egg-info/dependency_links.txt
countmemaybe.egg-info/requires.txt
countmemaybe.egg-info/top_level.txt