Metadata-Version: 2.1
Name: countmemaybe
Version: 0.5
Summary: A set of probabilstic distinct value estimators (ie: calculate the cardinality of big sets)
Home-page: http://github.com/mynameisfiber/countmemaybe/
Author: Micha Gorelick
Author-email: mynameisfiber@gmail.com
License: GNU Lesser General Public License v3 or later (LGPLv3+)
Download-URL: https://github.com/mynameisfiber/countmemaybe/tarball/master
Platform: UNKNOWN
Classifier: Programming Language :: Python
Classifier: Topic :: Scientific/Engineering
Classifier: Topic :: Software Development :: Libraries
Classifier: License :: OSI Approved :: GNU Lesser General Public License v3 or later (LGPLv3+)
Provides-Extra: kminvalue_relative_error
Provides-Extra: test_dve
